[
  {
    "slug": "seo-grandes-entreprises-strategie-2026",
    "title": "SEO pour grandes entreprises : la stratégie qui fait la différence en 2026",
    "keyword": "SEO grandes entreprises",
    "category": "SEO",
    "status": "done",
    "publishedAt": "2026-07-09",
    "publishedSlug": "seo-grandes-entreprises-strategie-2026"
  },
  {
    "slug": "referencement-naturel-roi-b2b",
    "title": "Le ROI du référencement naturel en B2B : comment le mesurer vraiment",
    "keyword": "ROI référencement naturel B2B",
    "category": "SEO",
    "status": "todo"
  },
  {
    "slug": "site-internet-vs-wordpress-entreprise",
    "title": "Site codé sur-mesure vs WordPress : que choisir pour une entreprise ?",
    "keyword": "site sur-mesure vs WordPress",
    "category": "Création de sites",
    "status": "todo"
  },
  {
    "slug": "generer-leads-b2b-linkedin-cold-email",
    "title": "Générer des leads B2B avec LinkedIn et le cold email : le duo gagnant",
    "keyword": "leads B2B LinkedIn cold email",
    "category": "Acquisition B2B",
    "status": "todo"
  },
  {
    "slug": "core-web-vitals-impact-conversion",
    "title": "Core Web Vitals : pourquoi la vitesse de votre site impacte vos ventes",
    "keyword": "Core Web Vitals conversion",
    "category": "Performance",
    "status": "todo"
  },
  {
    "slug": "audit-seo-checklist-complete",
    "title": "Audit SEO : la checklist complète pour diagnostiquer votre site",
    "keyword": "audit SEO checklist",
    "category": "SEO",
    "status": "todo"
  },
  {
    "slug": "cold-email-delivrabilite-guide",
    "title": "Cold email : le guide de la délivrabilité pour ne plus finir en spam",
    "keyword": "délivrabilité cold email",
    "category": "Acquisition B2B",
    "status": "todo"
  },
  {
    "slug": "tunnel-conversion-site-b2b",
    "title": "Construire un tunnel de conversion efficace sur un site B2B",
    "keyword": "tunnel de conversion B2B",
    "category": "Acquisition B2B",
    "status": "todo"
  },
  {
    "slug": "strategie-contenu-seo-entreprise",
    "title": "Stratégie de contenu SEO : le plan pour dominer votre marché",
    "keyword": "stratégie de contenu SEO",
    "category": "SEO",
    "status": "todo"
  },
  {
    "slug": "hebergement-web-performance-securite",
    "title": "Hébergement web : comment allier performance et sécurité",
    "keyword": "hébergement web performance sécurité",
    "category": "Hébergement",
    "status": "todo"
  },
  {
    "slug": "refonte-site-internet-sans-perdre-seo",
    "title": "Refonte de site internet : comment ne pas perdre votre SEO",
    "keyword": "refonte site internet SEO",
    "category": "Création de sites",
    "status": "todo"
  },
  {
    "slug": "mots-cles-intention-commerciale-b2b",
    "title": "Mots-clés à intention commerciale : la clé du SEO rentable en B2B",
    "keyword": "mots-clés intention commerciale",
    "category": "SEO",
    "status": "todo"
  },
  {
    "slug": "landing-page-haute-conversion",
    "title": "Landing page : les ingrédients d'une page qui convertit vraiment",
    "keyword": "landing page conversion",
    "category": "Acquisition B2B",
    "status": "todo"
  },
  {
    "slug": "netlinking-strategie-autorite",
    "title": "Netlinking : construire l'autorité de votre site sans risque",
    "keyword": "stratégie netlinking",
    "category": "SEO",
    "status": "todo"
  },
  {
    "slug": "prospection-commerciale-digitale-2026",
    "title": "Prospection commerciale digitale : les méthodes qui marchent en 2026",
    "keyword": "prospection commerciale digitale",
    "category": "Acquisition B2B",
    "status": "todo"
  },
  {
    "slug": "vitesse-site-web-optimisation",
    "title": "Optimiser la vitesse de votre site web : guide pratique",
    "keyword": "optimiser vitesse site web",
    "category": "Performance",
    "status": "todo"
  },
  {
    "slug": "seo-local-entreprise-multi-sites",
    "title": "SEO local pour les entreprises multi-établissements",
    "keyword": "SEO local multi-sites",
    "category": "SEO",
    "status": "todo"
  },
  {
    "slug": "email-marketing-b2b-segmentation",
    "title": "Email marketing B2B : la puissance de la segmentation",
    "keyword": "email marketing B2B segmentation",
    "category": "Acquisition B2B",
    "status": "todo"
  },
  {
    "slug": "google-eeat-confiance-contenu",
    "title": "Google E-E-A-T : comment gagner la confiance de l'algorithme",
    "keyword": "Google E-E-A-T",
    "category": "SEO",
    "status": "todo"
  },
  {
    "slug": "site-vitrine-vs-machine-a-clients",
    "title": "Site vitrine ou machine à clients ? La différence qui change tout",
    "keyword": "site vitrine machine à clients",
    "category": "Stratégie digitale",
    "status": "todo"
  },
  {
    "slug": "kpi-marketing-digital-suivre",
    "title": "Les KPI marketing digital à suivre pour piloter votre croissance",
    "keyword": "KPI marketing digital",
    "category": "Stratégie digitale",
    "status": "todo"
  },
  {
    "slug": "securite-site-web-entreprise",
    "title": "Sécurité d'un site web d'entreprise : les fondamentaux à maîtriser",
    "keyword": "sécurité site web entreprise",
    "category": "Hébergement",
    "status": "todo"
  },
  {
    "slug": "ia-seo-redaction-contenu",
    "title": "IA et SEO : comment l'intelligence artificielle change la rédaction web",
    "keyword": "IA et SEO",
    "category": "SEO",
    "status": "todo"
  },
  {
    "slug": "acquisition-client-b2b-canaux",
    "title": "Acquisition client B2B : quels canaux prioriser selon votre marché",
    "keyword": "acquisition client B2B canaux",
    "category": "Acquisition B2B",
    "status": "todo"
  }
]
